{
  "type": "excalidraw",
  "version": 2,
  "source": "https://excalidraw.com",
  "elements": [
    {
      "id": "qNb4LxGVb5Kpgm1GLBWCE",
      "type": "rectangle",
      "x": 580.3359375,
      "y": 294.7109375,
      "width": 215.0625,
      "height": 172.3125,
      "angle": 0,
      "strokeColor": "#1e1e1e",
      "backgroundColor": "transparent",
      "fillStyle": "solid",
      "strokeWidth": 2,
      "strokeStyle": "solid",
      "roughness": 1,
      "opacity": 100,
      "groupIds": [],
      "frameId": null,
      "index": "a0",
      "roundness": {
        "type": 3
      },
      "seed": 970093669,
      "version": 93,
      "versionNonce": 963452203,
      "isDeleted": false,
      "boundElements": null,
      "updated": 1759516185694,
      "link": null,
      "locked": false
    },
    {
      "id": "gB59KWRLzGvDVaXJr_e66",
      "type": "text",
      "x": 634.234375,
      "y": 359.328125,
      "width": 107.29994201660156,
      "height": 25,
      "angle": 0,
      "strokeColor": "#1e1e1e",
      "backgroundColor": "transparent",
      "fillStyle": "solid",
      "strokeWidth": 2,
      "strokeStyle": "solid",
      "roughness": 1,
      "opacity": 100,
      "groupIds": [],
      "frameId": null,
      "index": "a1",
      "roundness": null,
      "seed": 982955621,
      "version": 92,
      "versionNonce": 763125733,
      "isDeleted": false,
      "boundElements": null,
      "updated": 1759516296142,
      "link": null,
      "locked": false,
      "text": "Hello_world",
      "fontSize": 20,
      "fontFamily": 5,
      "textAlign": "left",
      "verticalAlign": "top",
      "containerId": null,
      "originalText": "Hello_world",
      "autoResize": true,
      "lineHeight": 1.25
    }
  ],
  "appState": {
    "gridSize": 20,
    "gridStep": 5,
    "gridModeEnabled": false,
    "viewBackgroundColor": "#ffffff",
    "lockedMultiSelections": {}
  },
  "files": {}
}